general_class_balancer/__init__.py
general_class_balancer/general_class_balancer.py
general_class_balancer-0.0.7.dist-info/METADATA
general_class_balancer-0.0.7.dist-info/WHEEL
general_class_balancer-0.0.7.dist-info/RECORD
