Metadata-Version: 2.4
Name: general_class_balancer
Version: 0.0.7
Summary: Matches datapoints from an imbalanced class to a balanced one.
Project-URL: Homepage, https://github.com/mleming/general_class_balancer
Author-email: Matt Leming <mleming@mgh.harvard.edu>
Maintainer-email: Matt Leming <mleming@mgh.harvard.edu>
License: MIT License
Keywords: biomedical,deep learning,ehr,machine learning,mri,pytorch
Requires-Python: >=3.8
Requires-Dist: matplotlib
Requires-Dist: numpy>=1.22.0
Requires-Dist: pandas
Requires-Dist: scipy>=1.9.3
